txweb/__init__.py
txweb/alipay.py
txweb/apiutils.py
txweb/beansmq.py
txweb/choosereactor.py
txweb/config.py
txweb/dbutils.py
txweb/dispatch.py
txweb/logger.py
txweb/mail.py
txweb/mcache.py
txweb/paginator.py
txweb/permit.py
txweb/redis_cache.py
txweb/redis_conf.py
txweb/redis_session.py
txweb/storage.py
txweb/taskd.py
txweb/txappctl.py
txweb/txwebctl.py
txweb/utils.py
txweb/validate.py
txweb/web.py
txweb/wxpay.py
txweb/btforms/__init__.py
txweb/btforms/dataform.py
txweb/btforms/net.py
txweb/btforms/rules.py
txweb/tests/__init__.py
txweb-0.0.8.dist-info/DESCRIPTION.rst
txweb-0.0.8.dist-info/entry_points.txt
txweb-0.0.8.dist-info/METADATA
txweb-0.0.8.dist-info/metadata.json
txweb-0.0.8.dist-info/RECORD
txweb-0.0.8.dist-info/top_level.txt
txweb-0.0.8.dist-info/WHEEL
txweb-0.0.8.dist-info/zip-safe
