Metadata-Version: 2.0
Name: txweb
Version: 0.0.8
Summary: python web framework
Home-page: https://github.com/talkincode/txweb
Author: jamiesun
Author-email: jamiesun.net@gmail.com
License: MIT
Keywords: toughstruct,cyclone,twisted,web
Platform: UNKNOWN
Classifier: Development Status :: 6 - Mature
Classifier: Intended Audience :: Developers
Classifier: Programming Language :: Python :: 2.6
Classifier: Programming Language :: Python :: 2.7
Classifier: Topic :: Software Development :: Libraries :: Python Modules
Requires-Dist: six (>=1.8.0)
Requires-Dist: Twisted (>=15.0.0)
Requires-Dist: pyOpenSSL (>=0.13)
Requires-Dist: cyclone
Requires-Dist: pycrypto
